setup.cfg
setup.py
bin/sshd-violations
bin/sshd-violations-agent
bin/zfs-snapshots
ultimatum/__init__.py
ultimatum/filesystems.py
ultimatum/sysctl.py
ultimatum.egg-info/PKG-INFO
ultimatum.egg-info/SOURCES.txt
ultimatum.egg-info/dependency_links.txt
ultimatum.egg-info/not-zip-safe
ultimatum.egg-info/requires.txt
ultimatum.egg-info/top_level.txt
ultimatum/hardware/__init__.py
ultimatum/hardware/coretemp.py
ultimatum/logformats/__init__.py
ultimatum/logformats/auth.py
ultimatum/zfs/__init__.py
ultimatum/zfs/snapshots.py
ultimatum/zfs/zfs.py
ultimatum/zfs/zpool.py