Metadata-Version: 1.0
Name: ultimatum
Version: 4.0.7
Summary: Sysadmin utility modules and scripts for FreeBSD
Home-page: https://github.com/hile/ultimatum
Author: Ilkka Tuohela
Author-email: hile@iki.fi
License: PSF
Keywords: System Management Utility FreeBSD Scripts
Platform: UNKNOWN
